arduino_dbg/__init__.py
arduino_dbg/__main__.py
arduino_dbg/binutils.py
arduino_dbg/breakpoint.py
arduino_dbg/conf_files.py
arduino_dbg/debugger.py
arduino_dbg/dump.py
arduino_dbg/eval_location.py
arduino_dbg/memory_map.py
arduino_dbg/protocol.py
arduino_dbg/repl.py
arduino_dbg/repl_command.py
arduino_dbg/serialize.py
arduino_dbg/show_info.py
arduino_dbg/stack.py
arduino_dbg/symbol.py
arduino_dbg/term.py
arduino_dbg/types.py
arduino_dbg/version.py
arduino_dbg/arch/__init__.py
arduino_dbg/arch/arm_thumb_common.conf
arduino_dbg/arch/atmega328p.conf
arduino_dbg/arch/atmega32u4.conf
arduino_dbg/arch/auto.conf
arduino_dbg/arch/avr_common.conf
arduino_dbg/arch/avr_interface.py
arduino_dbg/arch/defaults_common.conf
arduino_dbg/arch/samd51x19a.conf
arduino_dbg/arch/samd_common.conf
arduino_dbg/arch/thumb_interface.py
arduino_dbg/io/__init__.py
arduino_dbg/io/__main__.py
arduino_dbg/platforms/__init__.py
arduino_dbg/platforms/auto.conf
arduino_dbg/platforms/feather_m4.conf
arduino_dbg/platforms/leonardo.conf
arduino_dbg/platforms/uno.conf
arduino_dbg-0.2.0.dist-info/LICENSE.txt
arduino_dbg-0.2.0.dist-info/METADATA
arduino_dbg-0.2.0.dist-info/WHEEL
arduino_dbg-0.2.0.dist-info/entry_points.txt
arduino_dbg-0.2.0.dist-info/top_level.txt
arduino_dbg-0.2.0.dist-info/zip-safe
arduino_dbg-0.2.0.dist-info/RECORD
