Metadata-Version: 2.1
Name: arduino-dbg
Version: 0.2.0
Summary: Interactive debugger for Arduino device sketches
Home-page: https://github.com/kimballa/arduino-dbg
Author: Aaron Kimball
Author-email: akimball83@gmail.com
License: BSD 3-Clause License
Keywords: Arduino,debugger
Platform: UNKNOWN
Classifier: Development Status :: 3 - Alpha
Classifier: Environment :: Console
Classifier: Intended Audience :: Developers
Classifier: License :: OSI Approved :: BSD License
Classifier: Operating System :: POSIX
Classifier: Programming Language :: Python :: 3
Classifier: Topic :: Software Development :: Debuggers
Classifier: Topic :: Software Development :: Embedded Systems
Requires-Python: >=3.6
License-File: LICENSE.txt
Requires-Dist: pyelftools (>=0.27)
Requires-Dist: pyserial (>=3.5)
Requires-Dist: sortedcontainers (>=2.4.0)
